{
  "copyClipboard": "Копиране в клипборда",
  "error": "Грешка",
  "close": "Затваряне",
  "clear": "Изчистване",
  "expand": "Разгъване",
  "collapse": "Сгъване",
  "originError": {
    "message": "Приложението, в което се опитвате да влезете, не произхожда от предоставения от вас URL адрес",
    "close": "Затваряне",
    "options": "Разширени опции",
    "linkMessage": "Продължете към"
  },
  "licenseError": {
    "message": "Вашият акаунт не е лицензиран да използва Configurable Apps, които не са публични. Помолете администратора на Вашата организация да Ви направи тип потребител, който включва Основни приложения или допълнителен лиценз за Основни приложения.",
    "title": "Не е лицензиран"
  },
  "analyticsOptIn": "Включване",
  "tools": {
    "export": "Експортиране в PDF",
    "legend": "Отваряне на легендата",
    "layerList": "Отваряне на списък със слоеве",
    "search": "Отваряне на търсене",
    "print": "Отваряне на опцията за отпечатване",
    "bookmarks": "Отваряне на отметки",
    "time": "Време на отваряне",
    "overviewMap": "Отваряне на общ преглед на карта",
    "elevationProfile": "Отваряне на височинен профил",
    "table": "Отваряне на таблица",
    "screenshot": "Отваряне на екранна снимка",
    "splash": "Отваряне на панела за въведение",
    "hoverPopupTip": "Натиснете върху картата, за да закачите",
    "close": {
      "legend": "Затваряне на легенда",
      "layerList": "Затваряне на списък със слоеве",
      "search": "Затваряне на търсенето",
      "print": "Затваряне на опцията за отпечатване",
      "bookmarks": "Затваряне на отметки",
      "time": "Затваряне на модул за време",
      "overviewMap": "Затваряне на общи преглед на картата",
      "elevationProfile": "Затваряне на височинен профил",
      "table": "Затваряне на таблица",
      "screenshot": "Затваряне на екранна снимка",
      "splash": "Затваряне на панела за представяне",
      "cluster": "Търсене на обекти"
    }
  },
  "export": {
    "results": "Резултати",
    "resultsAndMap": "Резултати и карта",
    "tip": "Отпечатване или запазване като PDF"
  },
  "mapScroll": {
    "enableMessage": "Активиране на превъртане на картата",
    "disableMessage": "Деактивиране на превъртане на картата"
  },
  "generalShortcuts": {
    "menu": "Меню за бърз достъп",
    "shortcut": "Пряк път",
    "action": "Действие",
    "title": "Избор на карта",
    "label": "Клавишни комбинации"
  },
  "shortcutsMapView": {
    "arrowKeys": "Клавиши със стрелки",
    "nudge": "Преместване наляво, надясно, нагоре или надолу",
    "N": "Настройте така, че да сочи север.",
    "A": "Завъртане по посока, обратна на часовниковата стрелка",
    "D": "Завъртане по посока на часовниковата стрелка",
    "plus": "Приближаване към центъра",
    "minus": "Отдалечаване от центъра"
  },
  "shortcutsSceneView": {
    "P": "Преместете камерата, за да погледнете перпендикулярно на данните, показани на картата.",
    "N": "Настройте картата така, че да сочи север.",
    "W": "Наклонете камерата нагоре",
    "A": "Завъртете камерата по посока, обратна на часовниковата стрелка.",
    "D": "Завъртете камерата по посока на часовниковата стрелка.",
    "S": "Наклонете камерата надолу",
    "globalCommands": {
      "J": "Преместване надолу към картата",
      "U": "Преместване нагоре от картата"
    }
  }
}